[
  {
    "description": "",
    "elements": [
      {
        "description": "",
        "id": ";",
        "keyword": "Scenario",
        "line": 2,
        "name": "",
        "steps": [
          {
            "arguments": [],
            "keyword": "Given ",
            "line": 3,
            "match": {
              "location": "stepdefs.js:14"
            },
            "name": "this step is pending",
            "result": {
              "duration": 0,
              "status": "pending"
            }
          }
        ],
        "tags": [],
        "type": "scenario"
      }
    ],
    "id": "",
    "keyword": "Feature",
    "line": 1,
    "name": "",
    "tags": [],
    "uri": "../../features/one-pending-scenario-nn.feature"
  }
]
