[
  {
    "description": "",
    "elements": [
      {
        "after": [
          {
            "match": {
              "location": "stepdefs.rb:5"
            },
            "result": {
              "duration": 94000,
              "error_message": "Failing after hook (RuntimeError)\n./stepdefs.rb:6:in `After'",
              "status": "failed"
            }
          }
        ],
        "description": "",
        "id": ";",
        "keyword": "Scenario",
        "line": 3,
        "name": "",
        "steps": [
          {
            "keyword": "Given ",
            "line": 4,
            "match": {
              "location": "stepdefs.rb:13"
            },
            "name": "this step passes",
            "result": {
              "duration": 24000,
              "status": "passed"
            }
          }
        ],
        "tags": [
          {
            "line": 2,
            "name": "@failing_after"
          }
        ],
        "type": "scenario"
      },
      {
        "after": [
          {
            "match": {
              "location": "stepdefs.rb:5"
            },
            "result": {
              "duration": 84000,
              "error_message": "Failing after hook (RuntimeError)\n./stepdefs.rb:6:in `After'",
              "status": "failed"
            }
          }
        ],
        "description": "",
        "id": ";",
        "keyword": "Scenario",
        "line": 3,
        "name": "",
        "steps": [
          {
            "keyword": "Given ",
            "line": 4,
            "match": {
              "location": "stepdefs.rb:13"
            },
            "name": "this step passes",
            "result": {
              "duration": 7000,
              "status": "passed"
            }
          }
        ],
        "tags": [
          {
            "line": 2,
            "name": "@failing_after"
          }
        ],
        "type": "scenario"
      },
      {
        "after": [
          {
            "match": {
              "location": "stepdefs.rb:5"
            },
            "result": {
              "duration": 93000,
              "error_message": "Failing after hook (RuntimeError)\n./stepdefs.rb:6:in `After'",
              "status": "failed"
            }
          }
        ],
        "description": "",
        "id": ";",
        "keyword": "Scenario",
        "line": 3,
        "name": "",
        "steps": [
          {
            "keyword": "Given ",
            "line": 4,
            "match": {
              "location": "stepdefs.rb:13"
            },
            "name": "this step passes",
            "result": {
              "duration": 9000,
              "status": "passed"
            }
          }
        ],
        "tags": [
          {
            "line": 2,
            "name": "@failing_after"
          }
        ],
        "type": "scenario"
      }
    ],
    "id": "",
    "keyword": "Feature",
    "line": 1,
    "name": "",
    "uri": "../../features/failing-after-hook-nn.feature"
  }
]
