[
  {
    "description": "  Here is a description",
    "elements": [
      {
        "description": "",
        "keyword": "Background",
        "line": 4,
        "name": "",
        "steps": [
          {
            "keyword": "Given ",
            "line": 5,
            "match": {
              "location": "support/ruby/env.rb:17"
            },
            "name": "this step is decaying",
            "result": {
              "duration": 65022,
              "status": "passed"
            }
          },
          {
            "keyword": "Given ",
            "line": 8,
            "match": {
              "location": "support/ruby/env.rb:9"
            },
            "name": "this step passes",
            "result": {
              "duration": 15066,
              "status": "passed"
            }
          }
        ],
        "type": "background"
      },
      {
        "description": "",
        "keyword": "Background",
        "line": 4,
        "name": "",
        "steps": [
          {
            "keyword": "Given ",
            "line": 5,
            "match": {
              "location": "support/ruby/env.rb:17"
            },
            "name": "this step is decaying",
            "result": {
              "duration": 193880,
              "error_message": "Decayed (RuntimeError)\n./support/ruby/env.rb:20:in `/decaying/'\nfeatures/decaying-background.feature:5:in `Given this step is decaying'",
              "status": "failed"
            }
          },
          {
            "keyword": "Given ",
            "line": 11,
            "match": {
              "location": "support/ruby/env.rb:9"
            },
            "name": "this step passes",
            "result": {
              "status": "skipped"
            }
          }
        ],
        "type": "background"
      }
    ],
    "id": "",
    "keyword": "Feature",
    "line": 1,
    "name": "",
    "uri": "features/decaying-background.feature"
  }
]
