[
  {
    "description": "  Here is a description",
    "elements": [
      {
        "description": "",
        "keyword": "Background",
        "line": 4,
        "name": "",
        "steps": [
          {
            "keyword": "Given ",
            "line": 5,
            "match": {
              "location": "features/step_definitions/stepdefs.rb:16"
            },
            "name": "this step fails",
            "result": {
              "duration": 555561,
              "error_message": "Fail (RuntimeError)\n./features/step_definitions/stepdefs.rb:17:in `/fail/'\nfeatures/failing-background-with-two-scenarios.feature:5:in `Given this step fails'",
              "status": "failed"
            }
          }
        ],
        "type": "background"
      },
      {
        "description": "",
        "id": "failing-background-with-two-scenarios;s1",
        "keyword": "Scenario",
        "line": 7,
        "name": "S1",
        "steps": [
          {
            "keyword": "Given ",
            "line": 8,
            "match": {
              "location": "features/step_definitions/stepdefs.rb:13"
            },
            "name": "this step passes",
            "result": {
              "status": "skipped"
            }
          }
        ],
        "type": "scenario"
      },
      {
        "description": "",
        "keyword": "Background",
        "line": 4,
        "name": "",
        "steps": [
          {
            "keyword": "Given ",
            "line": 5,
            "match": {
              "location": "features/step_definitions/stepdefs.rb:16"
            },
            "name": "this step fails",
            "result": {
              "duration": 378455,
              "error_message": "Fail (RuntimeError)\n./features/step_definitions/stepdefs.rb:17:in `/fail/'\nfeatures/failing-background-with-two-scenarios.feature:5:in `Given this step fails'",
              "status": "failed"
            }
          }
        ],
        "type": "background"
      },
      {
        "description": "",
        "id": "failing-background-with-two-scenarios;s1",
        "keyword": "Scenario",
        "line": 7,
        "name": "S1",
        "steps": [
          {
            "keyword": "Given ",
            "line": 8,
            "match": {
              "location": "features/step_definitions/stepdefs.rb:13"
            },
            "name": "this step passes",
            "result": {
              "status": "skipped"
            }
          }
        ],
        "type": "scenario"
      },
      {
        "description": "",
        "keyword": "Background",
        "line": 4,
        "name": "",
        "steps": [
          {
            "keyword": "Given ",
            "line": 5,
            "match": {
              "location": "features/step_definitions/stepdefs.rb:16"
            },
            "name": "this step fails",
            "result": {
              "duration": 320846,
              "error_message": "Fail (RuntimeError)\n./features/step_definitions/stepdefs.rb:17:in `/fail/'\nfeatures/failing-background-with-two-scenarios.feature:5:in `Given this step fails'",
              "status": "failed"
            }
          }
        ],
        "type": "background"
      },
      {
        "description": "",
        "id": "failing-background-with-two-scenarios;s1",
        "keyword": "Scenario",
        "line": 7,
        "name": "S1",
        "steps": [
          {
            "keyword": "Given ",
            "line": 8,
            "match": {
              "location": "features/step_definitions/stepdefs.rb:13"
            },
            "name": "this step passes",
            "result": {
              "status": "skipped"
            }
          }
        ],
        "type": "scenario"
      },
      {
        "description": "",
        "keyword": "Background",
        "line": 4,
        "name": "",
        "steps": [
          {
            "keyword": "Given ",
            "line": 5,
            "match": {
              "location": "features/step_definitions/stepdefs.rb:16"
            },
            "name": "this step fails",
            "result": {
              "duration": 265771,
              "error_message": "Fail (RuntimeError)\n./features/step_definitions/stepdefs.rb:17:in `/fail/'\nfeatures/failing-background-with-two-scenarios.feature:5:in `Given this step fails'",
              "status": "failed"
            }
          }
        ],
        "type": "background"
      },
      {
        "description": "",
        "id": "failing-background-with-two-scenarios;s2",
        "keyword": "Scenario",
        "line": 10,
        "name": "S2",
        "steps": [
          {
            "keyword": "Given ",
            "line": 11,
            "match": {
              "location": "features/step_definitions/stepdefs.rb:13"
            },
            "name": "this step passes",
            "result": {
              "status": "skipped"
            }
          }
        ],
        "type": "scenario"
      },
      {
        "description": "",
        "keyword": "Background",
        "line": 4,
        "name": "",
        "steps": [
          {
            "keyword": "Given ",
            "line": 5,
            "match": {
              "location": "features/step_definitions/stepdefs.rb:16"
            },
            "name": "this step fails",
            "result": {
              "duration": 301753,
              "error_message": "Fail (RuntimeError)\n./features/step_definitions/stepdefs.rb:17:in `/fail/'\nfeatures/failing-background-with-two-scenarios.feature:5:in `Given this step fails'",
              "status": "failed"
            }
          }
        ],
        "type": "background"
      },
      {
        "description": "",
        "id": "failing-background-with-two-scenarios;s2",
        "keyword": "Scenario",
        "line": 10,
        "name": "S2",
        "steps": [
          {
            "keyword": "Given ",
            "line": 11,
            "match": {
              "location": "features/step_definitions/stepdefs.rb:13"
            },
            "name": "this step passes",
            "result": {
              "status": "skipped"
            }
          }
        ],
        "type": "scenario"
      },
      {
        "description": "",
        "keyword": "Background",
        "line": 4,
        "name": "",
        "steps": [
          {
            "keyword": "Given ",
            "line": 5,
            "match": {
              "location": "features/step_definitions/stepdefs.rb:16"
            },
            "name": "this step fails",
            "result": {
              "duration": 350211,
              "error_message": "Fail (RuntimeError)\n./features/step_definitions/stepdefs.rb:17:in `/fail/'\nfeatures/failing-background-with-two-scenarios.feature:5:in `Given this step fails'",
              "status": "failed"
            }
          }
        ],
        "type": "background"
      },
      {
        "description": "",
        "id": "failing-background-with-two-scenarios;s2",
        "keyword": "Scenario",
        "line": 10,
        "name": "S2",
        "steps": [
          {
            "keyword": "Given ",
            "line": 11,
            "match": {
              "location": "features/step_definitions/stepdefs.rb:13"
            },
            "name": "this step passes",
            "result": {
              "status": "skipped"
            }
          }
        ],
        "type": "scenario"
      }
    ],
    "id": "failing-background-with-two-scenarios",
    "keyword": "Feature",
    "line": 1,
    "name": "failing-background-with-two-scenarios",
    "uri": "features/failing-background-with-two-scenarios.feature"
  }
]
