[
  {
    "description": "",
    "elements": [
      {
        "description": "",
        "id": "failing-before-hook;s1",
        "keyword": "Scenario",
        "line": 3,
        "name": "S1",
        "steps": [
          {
            "keyword": "Given ",
            "line": 4,
            "match": {
              "location": "Steps.java:17"
            },
            "name": "this step passes",
            "result": {
              "duration": 243428364,
              "status": "passed"
            }
          }
        ],
        "tags": [
          {
            "name": "@failing_before"
          }
        ],
        "type": "scenario"
      }
    ],
    "id": "failing-before-hook",
    "keyword": "Feature",
    "line": 1,
    "name": "failing-before-hook",
    "tags": [],
    "uri": "features/failing-before-hook.feature"
  }
]
