[
  {
    "description": "",
    "elements": [
      {
        "after": [
          {
            "match": {
              "location": "support/ruby/env.rb:7"
            },
            "result": {
              "duration": 263939,
              "error_message": "Failing after hook (RuntimeError)\n./support/ruby/env.rb:8:in `After'",
              "status": "failed"
            }
          }
        ],
        "description": "",
        "id": ";",
        "keyword": "Scenario",
        "line": 3,
        "name": "",
        "steps": [
          {
            "keyword": "Given ",
            "line": 4,
            "match": {
              "location": "support/ruby/env.rb:11"
            },
            "name": "this step passes",
            "result": {
              "duration": 77566,
              "status": "passed"
            }
          }
        ],
        "tags": [
          {
            "line": 2,
            "name": "@failing-after"
          }
        ],
        "type": "scenario"
      }
    ],
    "id": "",
    "keyword": "Feature",
    "line": 1,
    "name": "",
    "uri": "features/failing-after-hook.feature"
  }
]
